go.mod
go.sum
hatch_build.py
main.go
cmd/check_lazy_imports.go
cmd/cherry-pick.go
cmd/db.go
cmd/db_drop.go
cmd/db_dump.go
cmd/db_migrate.go
cmd/db_restore.go
cmd/openapi.go
cmd/root.go
internal/_version.py
internal/alembic/alembic.go
internal/docker/docker.go
internal/lazyimports/lazyimports.go
internal/lazyimports/lazyimports_test.go
internal/openapi/openapi.go
internal/openapi/openapi_schema.py
internal/paths/paths.go
internal/postgres/postgres.go
internal/prompt/prompt.go
onyx_devtools-0.2.2.data/scripts/ods
onyx_devtools-0.2.2.dist-info/METADATA
onyx_devtools-0.2.2.dist-info/WHEEL
onyx_devtools-0.2.2.dist-info/RECORD
