Metadata-Version: 2.4
Name: onyx-devtools
Version: 0.2.2
Summary: Developer utilities for working on onyx.app
Project-URL: Repository, https://github.com/onyx-dot-app/onyx
Author-email: Onyx AI <founders@onyx.app>
Keywords: cli,devtools,onyx,tooling,tools
Classifier: License :: OSI Approved :: MIT License
Classifier: Operating System :: OS Independent
Classifier: Programming Language :: Go
Requires-Python: >=3.9
Requires-Dist: fastapi>=0.116.1
Requires-Dist: openapi-generator-cli>=7.17.0
